setup.py
kumo/__init__.py
kumo/loggly.py
kumo.egg-info/PKG-INFO
kumo.egg-info/SOURCES.txt
kumo.egg-info/dependency_links.txt
kumo.egg-info/requires.txt
kumo.egg-info/top_level.txt