Metadata-Version: 1.0
Name: kumo
Version: 0.2
Summary: Middleware that submits logs to cloud services like loggly and loggr.
Home-page: https://github.com/johnnykv/kumo
Author: jkv
Author-email: jkv@unixcluster.dk
License: UNKNOWN
Platform: UNKNOWN
